huaweicloudsdkccm/__init__.py
huaweicloudsdkccm/v1/__init__.py
huaweicloudsdkccm/v1/ccm_async_client.py
huaweicloudsdkccm/v1/ccm_client.py
huaweicloudsdkccm/v1/model/__init__.py
huaweicloudsdkccm/v1/model/batch_create_ca_tags_request.py
huaweicloudsdkccm/v1/model/batch_create_ca_tags_response.py
huaweicloudsdkccm/v1/model/batch_create_cert_tags_request.py
huaweicloudsdkccm/v1/model/batch_create_cert_tags_response.py
huaweicloudsdkccm/v1/model/batch_delete_ca_tags_request.py
huaweicloudsdkccm/v1/model/batch_delete_ca_tags_response.py
huaweicloudsdkccm/v1/model/batch_delete_cert_tags_request.py
huaweicloudsdkccm/v1/model/batch_delete_cert_tags_response.py
huaweicloudsdkccm/v1/model/batch_operate_tag_request_body.py
huaweicloudsdkccm/v1/model/cert_distinguished_name.py
huaweicloudsdkccm/v1/model/certificate_authorities.py
huaweicloudsdkccm/v1/model/certificates.py
huaweicloudsdkccm/v1/model/count_ca_resource_instances_request.py
huaweicloudsdkccm/v1/model/count_ca_resource_instances_response.py
huaweicloudsdkccm/v1/model/count_cert_resource_instances_request.py
huaweicloudsdkccm/v1/model/count_cert_resource_instances_response.py
huaweicloudsdkccm/v1/model/create_agency_request.py
huaweicloudsdkccm/v1/model/create_agency_response.py
huaweicloudsdkccm/v1/model/create_ca_tag_request.py
huaweicloudsdkccm/v1/model/create_ca_tag_response.py
huaweicloudsdkccm/v1/model/create_cert_tag_request.py
huaweicloudsdkccm/v1/model/create_cert_tag_response.py
huaweicloudsdkccm/v1/model/create_certificate_authority_obs_agency_request.py
huaweicloudsdkccm/v1/model/create_certificate_authority_obs_agency_response.py
huaweicloudsdkccm/v1/model/create_certificate_authority_order_request.py
huaweicloudsdkccm/v1/model/create_certificate_authority_order_request_body.py
huaweicloudsdkccm/v1/model/create_certificate_authority_order_response.py
huaweicloudsdkccm/v1/model/create_certificate_authority_request.py
huaweicloudsdkccm/v1/model/create_certificate_authority_request_body.py
huaweicloudsdkccm-3.1.184.dist-info/METADATA
huaweicloudsdkccm-3.1.184.dist-info/WHEEL
huaweicloudsdkccm-3.1.184.dist-info/licenses/LICENSE
huaweicloudsdkccm-3.1.184.dist-info/RECORD
